brynq_sdk_shiftbase/__init__.py
brynq_sdk_shiftbase/absence_policies.py
brynq_sdk_shiftbase/absence_types.py
brynq_sdk_shiftbase/absences.py
brynq_sdk_shiftbase/accounts.py
brynq_sdk_shiftbase/clock_ips_locations.py
brynq_sdk_shiftbase/contract_types.py
brynq_sdk_shiftbase/contracts.py
brynq_sdk_shiftbase/corrections.py
brynq_sdk_shiftbase/departments.py
brynq_sdk_shiftbase/employees.py
brynq_sdk_shiftbase/events.py
brynq_sdk_shiftbase/holidays.py
brynq_sdk_shiftbase/insights.py
brynq_sdk_shiftbase/kiosk.py
brynq_sdk_shiftbase/locations.py
brynq_sdk_shiftbase/logs.py
brynq_sdk_shiftbase/open_shifts.py
brynq_sdk_shiftbase/planning.py
brynq_sdk_shiftbase/reports.py
brynq_sdk_shiftbase/required_shifts.py
brynq_sdk_shiftbase/rosters.py
brynq_sdk_shiftbase/shiftbase.py
brynq_sdk_shiftbase/shifts.py
brynq_sdk_shiftbase/skills.py
brynq_sdk_shiftbase/team_days.py
brynq_sdk_shiftbase/teams.py
brynq_sdk_shiftbase/time_off_balances.py
brynq_sdk_shiftbase/timesheets.py
brynq_sdk_shiftbase/users.py
brynq_sdk_shiftbase/weather.py
brynq_sdk_shiftbase/schemas/__init__.py
brynq_sdk_shiftbase/schemas/absence_policies.py
brynq_sdk_shiftbase/schemas/absence_types.py
brynq_sdk_shiftbase/schemas/absences.py
brynq_sdk_shiftbase/schemas/accounts.py
brynq_sdk_shiftbase/schemas/clock_ips_locations.py
brynq_sdk_shiftbase/schemas/contract_types.py
brynq_sdk_shiftbase/schemas/contracts.py
brynq_sdk_shiftbase/schemas/corrections.py
brynq_sdk_shiftbase/schemas/departments.py
brynq_sdk_shiftbase/schemas/events.py
brynq_sdk_shiftbase/schemas/holidays.py
brynq_sdk_shiftbase/schemas/insights.py
brynq_sdk_shiftbase/schemas/kiosk.py
brynq_sdk_shiftbase/schemas/locations.py
brynq_sdk_shiftbase/schemas/logs.py
brynq_sdk_shiftbase/schemas/open_shifts.py
brynq_sdk_shiftbase/schemas/planning_conflicts.py
brynq_sdk_shiftbase/schemas/reports.py
brynq_sdk_shiftbase/schemas/required_shifts.py
brynq_sdk_shiftbase/schemas/rosters.py
brynq_sdk_shiftbase/schemas/shifts.py
brynq_sdk_shiftbase/schemas/skills.py
brynq_sdk_shiftbase-4.1.1.dist-info/METADATA
brynq_sdk_shiftbase-4.1.1.dist-info/WHEEL
brynq_sdk_shiftbase-4.1.1.dist-info/top_level.txt
brynq_sdk_shiftbase-4.1.1.dist-info/RECORD
