Metadata-Version: 2.4
Name: brynq_sdk_shiftbase
Version: 4.1.1
Summary: Shiftbase wrapper from BrynqQ
Author: D&A BrynQ
Author-email: support@brynq.com
License: BrynQ License
Requires-Dist: brynq_sdk_brynq<5,>=4
Requires-Dist: pandas<=3,>=1
Requires-Dist: requests<=3,>=2
Dynamic: author
Dynamic: author-email
Dynamic: description
Dynamic: license
Dynamic: requires-dist
Dynamic: summary
